pkgdemo/__init__.py
pkgdemo/demo.py
zjw_pkgdemo-0.0.1.dist-info/LICENSE
zjw_pkgdemo-0.0.1.dist-info/METADATA
zjw_pkgdemo-0.0.1.dist-info/WHEEL
zjw_pkgdemo-0.0.1.dist-info/top_level.txt
zjw_pkgdemo-0.0.1.dist-info/RECORD
